odoo/addons/account_analytic_tag/README.rst
odoo/addons/account_analytic_tag/__init__.py
odoo/addons/account_analytic_tag/__manifest__.py
odoo/addons/account_analytic_tag/i18n/account_analytic_tag.pot
odoo/addons/account_analytic_tag/i18n/ca.po
odoo/addons/account_analytic_tag/i18n/de.po
odoo/addons/account_analytic_tag/i18n/en_US.po
odoo/addons/account_analytic_tag/i18n/es.po
odoo/addons/account_analytic_tag/i18n/fr.po
odoo/addons/account_analytic_tag/i18n/it.po
odoo/addons/account_analytic_tag/i18n/pt_BR.po
odoo/addons/account_analytic_tag/i18n/zh_CN.po
odoo/addons/account_analytic_tag/models/__init__.py
odoo/addons/account_analytic_tag/models/account_analytic_line.py
odoo/addons/account_analytic_tag/models/account_analytic_tag.py
odoo/addons/account_analytic_tag/models/account_move_line.py
odoo/addons/account_analytic_tag/models/res_config_settings.py
odoo/addons/account_analytic_tag/readme/CONFIGURE.md
odoo/addons/account_analytic_tag/readme/CONTRIBUTORS.md
odoo/addons/account_analytic_tag/readme/DESCRIPTION.md
odoo/addons/account_analytic_tag/readme/USAGE.md
odoo/addons/account_analytic_tag/security/analytic_security.xml
odoo/addons/account_analytic_tag/security/ir.model.access.csv
odoo/addons/account_analytic_tag/static/description/icon.png
odoo/addons/account_analytic_tag/static/description/index.html
odoo/addons/account_analytic_tag/tests/__init__.py
odoo/addons/account_analytic_tag/tests/common.py
odoo/addons/account_analytic_tag/tests/test_account_analytic_tag.py
odoo/addons/account_analytic_tag/views/account_analytic_line_views.xml
odoo/addons/account_analytic_tag/views/account_analytic_tag_views.xml
odoo/addons/account_analytic_tag/views/account_move_line_views.xml
odoo/addons/account_analytic_tag/views/account_move_views.xml
odoo/addons/account_analytic_tag/views/res_config_settings_views.xml
odoo_addon_account_analytic_tag-19.0.1.0.0.2.dist-info/METADATA
odoo_addon_account_analytic_tag-19.0.1.0.0.2.dist-info/WHEEL
odoo_addon_account_analytic_tag-19.0.1.0.0.2.dist-info/top_level.txt
odoo_addon_account_analytic_tag-19.0.1.0.0.2.dist-info/RECORD
